hyperbox/__init__.py
hyperbox/run.py
hyperbox/train.py
hyperbox/callbacks/__init__.py
hyperbox/callbacks/wandb_callbacks.py
hyperbox/configs/__init__.py
hyperbox/configs/config.yaml
hyperbox/configs/lite.yaml
hyperbox/configs/callbacks/default.yaml
hyperbox/configs/callbacks/none.yaml
hyperbox/configs/callbacks/wandb.yaml
hyperbox/configs/datamodule/cifar100_datamodule.yaml
hyperbox/configs/datamodule/cifar10_datamodule.yaml
hyperbox/configs/datamodule/fakedata_datamodule.yaml
hyperbox/configs/datamodule/imagenet_dali_datamodule.yaml
hyperbox/configs/datamodule/imagenet_datamodule.yaml
hyperbox/configs/datamodule/medmnist_datamodule.yaml
hyperbox/configs/datamodule/mnist_datamodule.yaml
hyperbox/configs/datamodule/transforms/cifar.yaml
hyperbox/configs/engine/none.yaml
hyperbox/configs/experiment/example_bnnas.yaml
hyperbox/configs/experiment/example_classify.yaml
hyperbox/configs/experiment/example_darts_nas.yaml
hyperbox/configs/experiment/example_full.yaml
hyperbox/configs/experiment/example_nasbench.yaml
hyperbox/configs/experiment/example_ofa_nas.yaml
hyperbox/configs/experiment/example_random_nas.yaml
hyperbox/configs/experiment/example_repnas.yaml
hyperbox/configs/experiment/example_simple.yaml
hyperbox/configs/hparams_search/mnist_optuna.yaml
hyperbox/configs/hydra/default.yaml
hyperbox/configs/logger/comet.yaml
hyperbox/configs/logger/csv.yaml
hyperbox/configs/logger/many_loggers.yaml
hyperbox/configs/logger/mlflow.yaml
hyperbox/configs/logger/neptune.yaml
hyperbox/configs/logger/tensorboard.yaml
hyperbox/configs/logger/wandb.yaml
hyperbox/configs/model/classify_model.yaml
hyperbox/configs/model/darts_model.yaml
hyperbox/configs/model/mnist_model.yaml
hyperbox/configs/model/nasbench_model.yaml
hyperbox/configs/model/ofa_model.yaml
hyperbox/configs/model/random_model.yaml
hyperbox/configs/model/repnas_model.yaml
hyperbox/configs/model/resnet18.yaml
hyperbox/configs/model/loss_cfg/cross_entropy.yaml
hyperbox-1.4.3.dist-info/LICENSE
hyperbox-1.4.3.dist-info/METADATA
hyperbox-1.4.3.dist-info/WHEEL
hyperbox-1.4.3.dist-info/top_level.txt
hyperbox-1.4.3.dist-info/RECORD
