Metadata-Version: 2.1
Name: hyperbox
Version: 1.4.3
Summary: Hyperbox: An easy-to-use NAS framework.
Home-page: https://github.com/marsggbo/hyperbox
Author: marsggbo
License-File: LICENSE
Requires-Dist: torch (>=1.8.1)
Requires-Dist: torchvision
Requires-Dist: pytorch-lightning (==1.8.6)
Requires-Dist: torchmetrics (>=0.3.2)
Requires-Dist: lightning-bolts (>=0.3.3)
Requires-Dist: hydra-core (==1.2.0)
Requires-Dist: hydra-colorlog (==1.1.0.dev1)
Requires-Dist: hydra-optuna-sweeper (==1.1.0.dev2)
Requires-Dist: wandb (>=0.12.21)
Requires-Dist: pre-commit
Requires-Dist: black
Requires-Dist: isort
Requires-Dist: flake8
Requires-Dist: loguru (>=0.6.0)
Requires-Dist: einops
Requires-Dist: colorlog
Requires-Dist: scikit-learn
Requires-Dist: graphviz (>=0.20.1)
Requires-Dist: peewee
Requires-Dist: ipdb (>=0.13.9)
Requires-Dist: jupyterlab
Requires-Dist: pyrootutils
Requires-Dist: rich
Requires-Dist: pytest
Requires-Dist: sh
Requires-Dist: seaborn
Requires-Dist: pudb
